xbrl.py
xbrl-0.0.1.dist-info/LICENSE.txt
xbrl-0.0.1.dist-info/METADATA
xbrl-0.0.1.dist-info/WHEEL
xbrl-0.0.1.dist-info/top_level.txt
xbrl-0.0.1.dist-info/RECORD
